amartool/__init__.py
amartool-0.1.dist-info/licenses/LICENCE
amartool-0.1.dist-info/METADATA
amartool-0.1.dist-info/WHEEL
amartool-0.1.dist-info/top_level.txt
amartool-0.1.dist-info/RECORD
