Metadata-Version: 2.4
Name: amartool
Version: 0.1
Summary: A simple statistics tools package
License: MIT
Requires-Python: >=3.6
License-File: LICENCE
Requires-Dist: numpy
Requires-Dist: scipy
Dynamic: license
Dynamic: license-file
Dynamic: requires-dist
Dynamic: requires-python
Dynamic: summary
